pillar_gguf_scanner/__init__.py
pillar_gguf_scanner/cli.py
pillar_gguf_scanner/exceptions.py
pillar_gguf_scanner/heuristics.py
pillar_gguf_scanner/models.py
pillar_gguf_scanner/pillar_client.py
pillar_gguf_scanner/py.typed
pillar_gguf_scanner/reader.py
pillar_gguf_scanner/remote.py
pillar_gguf_scanner/scanner.py
pillar_gguf_scanner-0.0.3.dist-info/licenses/LICENSE
pillar_gguf_scanner-0.0.3.dist-info/METADATA
pillar_gguf_scanner-0.0.3.dist-info/WHEEL
pillar_gguf_scanner-0.0.3.dist-info/entry_points.txt
pillar_gguf_scanner-0.0.3.dist-info/top_level.txt
pillar_gguf_scanner-0.0.3.dist-info/RECORD
