Metadata-Version: 2.4
Name: pillar-gguf-scanner
Version: 0.0.3
Summary: Fast, programmatic scanning utilities for GGUF chat templates.
Author: Pillar Security
License: Apache-2.0
Project-URL: Homepage, https://pillar.security
Classifier: Programming Language :: Python :: 3
Classifier: Operating System :: OS Independent
Requires-Python: >=3.9
License-File: LICENSE
Requires-Dist: gguf>=0.6
Requires-Dist: httpx>=0.25
Requires-Dist: rich>=13.0
Dynamic: license-file
